dream_trainer/__init__.py
dream_trainer/py.typed
dream_trainer/callbacks/__init__.py
dream_trainer/callbacks/callback.py
dream_trainer/callbacks/fp8.py
dream_trainer/callbacks/ft.py
dream_trainer/callbacks/graph_breaks.py
dream_trainer/callbacks/optimize_fsdp.py
dream_trainer/callbacks/profile.py
dream_trainer/callbacks/progress_bar.py
dream_trainer/callbacks/trainer_summary.py
dream_trainer/callbacks/checkpoint/__init__.py
dream_trainer/callbacks/checkpoint/async_checkpoint.py
dream_trainer/callbacks/checkpoint/base.py
dream_trainer/callbacks/checkpoint/types.py
dream_trainer/callbacks/checkpoint/utils.py
dream_trainer/callbacks/loggers/__init__.py
dream_trainer/callbacks/loggers/base.py
dream_trainer/callbacks/loggers/dist.py
dream_trainer/callbacks/loggers/media.py
dream_trainer/callbacks/loggers/metric.py
dream_trainer/callbacks/loggers/wandb_watch.py
dream_trainer/configs/__init__.py
dream_trainer/configs/checkpoint.py
dream_trainer/configs/logger.py
dream_trainer/configs/trainer.py
dream_trainer/trainer/__init__.py
dream_trainer/trainer/abstract.py
dream_trainer/trainer/base.py
dream_trainer/trainer/dream.py
dream_trainer/trainer/mixins/__init__.py
dream_trainer/trainer/mixins/eval_metric.py
dream_trainer/trainer/mixins/quantize.py
dream_trainer/trainer/mixins/loggers/__init__.py
dream_trainer/trainer/mixins/loggers/types.py
dream_trainer/trainer/mixins/loggers/wandb.py
dream_trainer/trainer/mixins/setup/__init__.py
dream_trainer/trainer/mixins/setup/dataloader.py
dream_trainer/trainer/mixins/setup/models.py
dream_trainer/trainer/mixins/setup/optimizers.py
dream_trainer/trainer/mixins/setup/setup.py
dream_trainer/trainer/world/__init__.py
dream_trainer/trainer/world/distributed_world.py
dream_trainer/trainer/world/fault_tolerant_world.py
dream_trainer/trainer/world/ray_world.py
dream_trainer/utils/__init__.py
dream_trainer/utils/_logger.py
dream_trainer/utils/common.py
dream_trainer/utils/dataloader.py
dream_trainer/utils/entrypoint.py
dream_trainer-0.1.1.dist-info/METADATA
dream_trainer-0.1.1.dist-info/WHEEL
dream_trainer-0.1.1.dist-info/licenses/LICENSE
dream_trainer-0.1.1.dist-info/RECORD
