Metadata-Version: 2.4
Name: dream-trainer
Version: 0.1.1
Summary: Add your description here
Author-email: Tony Francis <tony@dream3d.com>, Vikaas Varma <vik@dream3d.com>
License-File: LICENSE
Requires-Python: >=3.10
Requires-Dist: dist-util==0.1.0
Requires-Dist: loguru>=0.7.3
Requires-Dist: torch>=2.7.1
Requires-Dist: tqdm>=4.67.1
Provides-Extra: metrics
Requires-Dist: torchmetrics>=1.7.1; extra == 'metrics'
Provides-Extra: rich
Requires-Dist: rich>=14.0.0; extra == 'rich'
Provides-Extra: torchao
Requires-Dist: torchao>=0.11.0; extra == 'torchao'
Provides-Extra: torchft
Requires-Dist: torchft; extra == 'torchft'
Provides-Extra: wandb
Requires-Dist: wandb[media]>=0.19.11; extra == 'wandb'
